clamnotif/__init__.py
clamnotif/__main__.py
clamnotif/_version.txt
clamnotif/checkcfg.py
clamnotif/checkreport.py
clamnotif/clamreport.py
clamnotif/config.py
clamnotif/default.py
clamnotif/echo.py
clamnotif/lastlog.py
clamnotif/messenger.py
clamnotif/reportreader.py
clamnotif/terminal.py
clamnotif/testsmtp.py
clamnotif/timeutils.py
clamnotif/welcome.py
test/__init__.py
test/test_checkcfg.py
test/test_checkreport.py
test/test_clamreport.py
test/test_config.py
test/test_lastlog.py
test/test_messenger.py
test/test_reportreader.py
test/test_terminal.py
test/test_testsmtp.py
test/test_timeutils.py
test/test_welcome.py
test/testutils.py
clamnotif-0.1.0.dist-info/LICENSE
clamnotif-0.1.0.dist-info/METADATA
clamnotif-0.1.0.dist-info/WHEEL
clamnotif-0.1.0.dist-info/top_level.txt
clamnotif-0.1.0.dist-info/RECORD
