Metadata-Version: 2.1
Name: clamnotif
Version: 0.1.0
Summary: A handy and simple tool for sending ClamAV notifications.
Home-page: https://github.com/pisoftmacao/clamnotif
Author: PiSoft Company Ltd.
Author-email: developer@pisoft.com.mo
License: UNKNOWN
Platform: UNKNOWN
Classifier: Programming Language :: Python :: 3
Classifier: License :: OSI Approved :: MIT License
Classifier: Operating System :: OS Independent
Requires-Python: >=3.6
License-File: LICENSE
